vvcontrollers/__init__.py
vvcontrollers/abstract.py
vvcontrollers/application.py
vvcontrollers/core.py
vvcontrollers/dialog.py
vvcontrollers/menu.py
vvcontrollers_yarmenti-0.1.1.dist-info/LICENSE
vvcontrollers_yarmenti-0.1.1.dist-info/METADATA
vvcontrollers_yarmenti-0.1.1.dist-info/WHEEL
vvcontrollers_yarmenti-0.1.1.dist-info/top_level.txt
vvcontrollers_yarmenti-0.1.1.dist-info/RECORD
