Metadata-Version: 2.1
Name: vvcontrollers-yarmenti
Version: 0.1.1
Summary: Helpers to use voila-vuetify template for voila-dashboards.
Home-page: https://github.com/yarmenti/py_vvcontrollers
Author: yarmenti
Author-email: yannick.armenti@gmail.com
License: UNKNOWN
Platform: UNKNOWN
Classifier: Programming Language :: Python :: 3
Classifier: License :: OSI Approved :: MIT License
Classifier: Operating System :: OS Independent
Requires-Python: >=3.6
Requires-Dist: pubsub-yarmenti (>=0.2.2)
Requires-Dist: ipyvuetify (>=1.1.1)
